{
  "ticker": "ASML",
  "name": "ASML Holding N.V. - New York Re",
  "price": 1087.99,
  "market_cap": 422300778496,
  "revenue_ttm": 37394938472.25447,
  "ocf_ttm": 13224169955.885767,
  "capex_ttm": 2815997213.837938,
  "sbc_ttm": 215695379.6145809,
  "buyback_ttm": 4933828651.033201,
  "total_debt": 3139888553.5175295,
  "cash_and_equivalents": 5953331785.465521,
  "shares_outstanding": 388147674,
  "beta": 1.35,
  "analyst_growth_estimate": 0.7,
  "forward_eps": 26.7,
  "dividend_yield": 70.0,
  "sector_type": "Semiconductor",
  "currency_code": "USD",
  "last_updated": "2025-12-02T01:21:36Z"
}