{
  "ticker": "RY",
  "name": "Royal Bank Of Canada",
  "price": 165.29,
  "market_cap": 232221999104,
  "revenue_ttm": 48294184257.13539,
  "net_income_ttm": 14780349002.6422,
  "ocf_ttm": 40083040562.12073,
  "capex_ttm": 1628146685.6363056,
  "sbc_ttm": 0.0,
  "buyback_ttm": 11501553381.144566,
  "total_debt": 395922737435.0338,
  "cash_and_equivalents": 119972561772.30626,
  "book_value_ttm": 100963967364.47838,
  "shares_outstanding": 1400211987,
  "beta": 1.01,
  "roe": 15.29,
  "analyst_growth_estimate": 13.8,
  "forward_eps": 12.4758415,
  "dividend_yield": 283.0,
  "sector_type": "Financial",
  "currency_code": "USD",
  "last_updated": "2025-12-18T06:29:48Z"
}