{
  "ticker": "RY",
  "name": "Royal Bank Of Canada",
  "price": 153.19,
  "market_cap": 216044863488,
  "revenue_ttm": 45907470772.740234,
  "ocf_ttm": 62140718562.87425,
  "capex_ttm": 1685913886.5126889,
  "sbc_ttm": 0.0,
  "buyback_ttm": 8453806672.369546,
  "total_debt": 373095950955.23236,
  "cash_and_equivalents": 76811377245.50897,
  "shares_outstanding": 1410306580,
  "beta": 1.008,
  "analyst_growth_estimate": 15.3,
  "forward_eps": 9.27,
  "sector_type": "Financial",
  "currency_code": "USD",
  "last_updated": "2025-11-28T02:33:08Z"
}